pyedm4hep/__init__.py
pyedm4hep/dataset.py
pyedm4hep/decay.py
pyedm4hep/event.py
pyedm4hep/hits.py
pyedm4hep/particle.py
pyedm4hep/plotting.py
pyedm4hep/utils.py
pyedm4hep-0.1.1.dist-info/licenses/LICENSE
pyedm4hep-0.1.1.dist-info/METADATA
pyedm4hep-0.1.1.dist-info/WHEEL
pyedm4hep-0.1.1.dist-info/top_level.txt
pyedm4hep-0.1.1.dist-info/RECORD
