Metadata-Version: 2.4
Name: pyedm4hep
Version: 0.1.1
Summary: A Python library for working with EDM4hep data, providing an object-oriented interface on top of Pandas DataFrames.
Author-email: Daniel Murnane <daniel.thomas.murnane@cern.ch>
Project-URL: Homepage, https://github.com/murnanedaniel/pyEDM4hep
Project-URL: Bug Tracker, https://github.com/murnanedaniel/pyEDM4hep/issues
Classifier: Programming Language :: Python :: 3
Classifier: License :: OSI Approved :: MIT License
Classifier: Operating System :: OS Independent
Classifier: Intended Audience :: Science/Research
Classifier: Topic :: Scientific/Engineering :: Physics
Requires-Python: >=3.8
License-File: LICENSE
Requires-Dist: pandas>=1.0
Requires-Dist: numpy>=1.18
Requires-Dist: uproot>=5.0
Requires-Dist: networkx>=2.5
Requires-Dist: matplotlib>=3.3
Requires-Dist: seaborn>=0.11
Requires-Dist: scipy
Provides-Extra: test
Requires-Dist: pytest>=6.0; extra == "test"
Requires-Dist: pytest-cov>=2.10; extra == "test"
Requires-Dist: uproot>=5.0; extra == "test"
Requires-Dist: pandas>=1.0; extra == "test"
Requires-Dist: numpy>=1.18; extra == "test"
Dynamic: license-file
